dm_logger/__init__.py
dm_logger/filters.py
dm_logger/formatter.py
dm_logger/logger.py
dm_logger-0.6.5.dist-info/METADATA
dm_logger-0.6.5.dist-info/WHEEL
dm_logger-0.6.5.dist-info/top_level.txt
dm_logger-0.6.5.dist-info/RECORD
