Metadata-Version: 2.4
Name: dm-logger
Version: 0.6.5
Summary: This is my custom logger
Home-page: https://pypi.org/project/dm-logger
Author: dimka4621
Author-email: mismartconfig@gmail.com
Project-URL: GitHub, https://github.com/MykhLibs/dm-logger
Keywords: dm-logger
Classifier: Programming Language :: Python :: 3.8
Classifier: License :: OSI Approved :: MIT License
Classifier: Operating System :: OS Independent
Requires-Python: >=3.8
Dynamic: author
Dynamic: author-email
Dynamic: classifier
Dynamic: description
Dynamic: description-content-type
Dynamic: home-page
Dynamic: keywords
Dynamic: project-url
Dynamic: requires-python
Dynamic: summary
